solace_semp_monitor/__init__.py
solace_semp_monitor/api_client.py
solace_semp_monitor/configuration.py
solace_semp_monitor/rest.py
solace_semp_monitor/api/__init__.py
solace_semp_monitor/api/about_api.py
solace_semp_monitor/api/acl_profile_api.py
solace_semp_monitor/api/all_api.py
solace_semp_monitor/api/authentication_oauth_provider_api.py
solace_semp_monitor/api/authorization_group_api.py
solace_semp_monitor/api/bridge_api.py
solace_semp_monitor/api/cert_authority_api.py
solace_semp_monitor/api/client_api.py
solace_semp_monitor/api/client_cert_authority_api.py
solace_semp_monitor/api/client_profile_api.py
solace_semp_monitor/api/client_username_api.py
solace_semp_monitor/api/config_sync_remote_node_api.py
solace_semp_monitor/api/distributed_cache_api.py
solace_semp_monitor/api/dmr_bridge_api.py
solace_semp_monitor/api/dmr_cluster_api.py
solace_semp_monitor/api/domain_cert_authority_api.py
solace_semp_monitor/api/guaranteed_msging_external_disk_array_api.py
solace_semp_monitor/api/jndi_api.py
solace_semp_monitor/api/mqtt_retain_cache_api.py
solace_semp_monitor/api/mqtt_session_api.py
solace_semp_monitor/api/msg_vpn_api.py
solace_semp_monitor/api/queue_api.py
solace_semp_monitor/api/queue_template_api.py
solace_semp_monitor/api/replay_log_api.py
solace_semp_monitor/api/replicated_topic_api.py
solace_semp_monitor/api/rest_delivery_point_api.py
solace_semp_monitor/api/standard_domain_cert_authority_api.py
solace_semp_monitor/api/topic_endpoint_api.py
solace_semp_monitor/api/topic_endpoint_template_api.py
solace_semp_monitor/api/transaction_api.py
solace_semp_monitor/api/virtual_hostname_api.py
solace_semp_monitor/models/__init__.py
solace_semp_monitor/models/about.py
solace_semp_monitor/models/about_api.py
solace_semp_monitor/models/about_api_collections.py
solace_semp_monitor/models/about_api_links.py
solace_semp_monitor/models/about_api_response.py
solace_semp_monitor/models/about_collections.py
solace_semp_monitor/models/about_links.py
solace_semp_monitor-9.8.0.12.dist-info/METADATA
solace_semp_monitor-9.8.0.12.dist-info/WHEEL
solace_semp_monitor-9.8.0.12.dist-info/top_level.txt
solace_semp_monitor-9.8.0.12.dist-info/RECORD
