Metadata-Version: 2.1
Name: solace-semp-monitor
Version: 9.8.0.12
Summary: SEMP (Solace Element Management Protocol)
Home-page: https://github.com/unixunion/solace_semp_client.git
Author: UNKNOWN
Author-email: support@solace.com
License: UNKNOWN
Keywords: Swagger,SEMP (Solace Element Management Protocol)
Platform: UNKNOWN
Requires-Dist: certifi (>=2017.4.17)
Requires-Dist: python-dateutil (>=2.1)
Requires-Dist: six (>=1.10)
Requires-Dist: urllib3 (>=1.23)
